train_lle/__init__.py
train_lle/cli.py
train_lle/dataset.py
train_lle/engine.py
train_lle/export.py
train_lle/loss.py
train_lle/models.py
train_lle/optimizer.py
train_lle/tensor.py
train_lle-1.0.1.dist-info/METADATA
train_lle-1.0.1.dist-info/WHEEL
train_lle-1.0.1.dist-info/entry_points.txt
train_lle-1.0.1.dist-info/top_level.txt
train_lle-1.0.1.dist-info/RECORD
