Metadata-Version: 2.4
Name: train-lle
Version: 1.0.1
Summary: Local Learning Engine - Python package
Author: Ramkrishna
License: Apache-2.0
Requires-Python: >=3.8
Requires-Dist: numpy
